metal_python/__init__.py
metal_python/api_client.py
metal_python/configuration.py
metal_python/driver.py
metal_python/rest.py
metal_python/api/__init__.py
metal_python/api/audit_api.py
metal_python/api/filesystemlayout_api.py
metal_python/api/firewall_api.py
metal_python/api/firmware_api.py
metal_python/api/health_api.py
metal_python/api/image_api.py
metal_python/api/ip_api.py
metal_python/api/machine_api.py
metal_python/api/network_api.py
metal_python/api/partition_api.py
metal_python/api/project_api.py
metal_python/api/size_api.py
metal_python/api/sizeimageconstraint_api.py
metal_python/api/switch_api.py
metal_python/api/tenant_api.py
metal_python/api/user_api.py
metal_python/api/version_api.py
metal_python/api/vpn_api.py
metal_python/models/__init__.py
metal_python/models/datastore_image_search_query.py
metal_python/models/datastore_ip_search_query.py
metal_python/models/datastore_machine_search_query.py
metal_python/models/datastore_network_search_query.py
metal_python/models/datastore_switch_search_query.py
metal_python/models/httperrors_http_error_response.py
metal_python/models/metal_switch_bgp_port_state.py
metal_python/models/rest_health_response.py
metal_python/models/rest_version.py
metal_python/models/v1_audit_find_request.py
metal_python/models/v1_audit_response.py
metal_python/models/v1_bgp_filter.py
metal_python/models/v1_board_revisions.py
metal_python/models/v1_boot_info.py
metal_python/models/v1_chassis_identify_led_state.py
metal_python/models/v1_common.py
metal_python/models/v1_describable.py
metal_python/models/v1_disk.py
metal_python/models/v1_disk_partition.py
metal_python/models/v1_dns_server.py
metal_python/models/v1_empty_body.py
metal_python/models/v1_filesystem.py
metal_python/models/v1_filesystem_layout_base.py
metal_python/models/v1_filesystem_layout_constraints.py
metal_python/models/v1_filesystem_layout_create_request.py
metal_python/models/v1_filesystem_layout_match_request.py
metal_python/models/v1_filesystem_layout_response.py
metal_python-0.43.0.dist-info/licenses/LICENSE
metal_python-0.43.0.dist-info/METADATA
metal_python-0.43.0.dist-info/WHEEL
metal_python-0.43.0.dist-info/top_level.txt
metal_python-0.43.0.dist-info/RECORD
