Metadata-Version: 2.4
Name: metal_python
Version: 0.43.0
Summary: Python API client for metal-api
Home-page: https://github.com/metal-stack/metal-python
Author: metal-stack authors
License: MIT
Keywords: metal-stack,metal-api,swagger,swagger-client
Classifier: License :: OSI Approved :: MIT License
Classifier: Intended Audience :: Developers
Classifier: License :: OSI Approved :: MIT License
Classifier: Natural Language :: English
Classifier: Operating System :: POSIX
Classifier: Programming Language :: Python :: 3
Classifier: Programming Language :: Python :: 3.5
Classifier: Programming Language :: Python :: 3.6
Classifier: Programming Language :: Python :: 3.7
Classifier: Programming Language :: Python :: 3.8
License-File: LICENSE
Requires-Dist: certifi>=2017.4.17
Requires-Dist: python-dateutil>=2.1
Requires-Dist: six>=1.10
Requires-Dist: urllib3>=1.23
Requires-Dist: wrapt
Provides-Extra: dev
Requires-Dist: coverage; extra == "dev"
Dynamic: author
Dynamic: classifier
Dynamic: home-page
Dynamic: keywords
Dynamic: license
Dynamic: license-file
Dynamic: provides-extra
Dynamic: requires-dist
Dynamic: summary
